pydantic_ai_unofficial_models/__init__.py
pydantic_ai_unofficial_models/main.py
pydantic_ai_unofficial_models/meta_ai_api.py
pydantic_ai_unofficial_models-0.2.0.dist-info/METADATA
pydantic_ai_unofficial_models-0.2.0.dist-info/WHEEL
pydantic_ai_unofficial_models-0.2.0.dist-info/top_level.txt
pydantic_ai_unofficial_models-0.2.0.dist-info/RECORD
