Metadata-Version: 2.4
Name: pydantic_ai_unofficial_models
Version: 0.2.0
Summary: A collection of unofficial models for pydantic-ai
Home-page: https://github.com/mr-destructive/pydantic-ai-unofficial-models
Author: Meet Gor
Author-email: gormeet711@gmail.com
Project-URL: Source, https://github.com/mr-destructive/meta_ai_api_tool_call
Project-URL: Tracker, https://github.com/mr-destructive/meta_ai_api_tool_call/issues
Classifier: Programming Language :: Python :: 3
Classifier: License :: OSI Approved :: MIT License
Classifier: Operating System :: OS Independent
Classifier: Intended Audience :: Developers
Classifier: Development Status :: 3 - Alpha
Classifier: Topic :: Software Development :: Libraries :: Python Modules
Requires-Python: >=3.7
Requires-Dist: pydantic-ai
Requires-Dist: meta-ai-api-tool-call
Dynamic: author
Dynamic: author-email
Dynamic: classifier
Dynamic: description
Dynamic: description-content-type
Dynamic: home-page
Dynamic: project-url
Dynamic: requires-dist
Dynamic: requires-python
Dynamic: summary
